pymongo_schema/__init__.py
pymongo_schema/__main__.py
pymongo_schema/compare.py
pymongo_schema/export.py
pymongo_schema/extract.py
pymongo_schema/filter.py
pymongo_schema/mongo_sql_types.py
pymongo_schema/tosql.py
pymongo_schema-0.4.2.dist-info/licenses/LICENSE
pymongo_schema-0.4.2.dist-info/METADATA
pymongo_schema-0.4.2.dist-info/WHEEL
pymongo_schema-0.4.2.dist-info/entry_points.txt
pymongo_schema-0.4.2.dist-info/top_level.txt
pymongo_schema-0.4.2.dist-info/RECORD
