Metadata-Version: 2.4
Name: pymongo-schema
Version: 0.4.2
Summary: A schema analyser for MongoDB written in Python
Home-page: https://github.com/pajachiet/pymongo-schema
Author: Pierre-Alain Jachiet
Author-email: pajachiet@gmail.com
License: GNU General Public License v3.0
Keywords: mongo,mongodb,schema,mongo-connector,mongo-connector-postgresql
License-File: LICENSE
Requires-Dist: pymongo>=4.0.0
Requires-Dist: pyyaml
Requires-Dist: docopt
Requires-Dist: ete4
Requires-Dist: pandas
Requires-Dist: xlwt
Requires-Dist: xlsxwriter
Requires-Dist: openpyxl
Requires-Dist: jinja2
Requires-Dist: future>=0.18.0
Requires-Dist: scipy
Dynamic: author
Dynamic: author-email
Dynamic: description
Dynamic: description-content-type
Dynamic: home-page
Dynamic: keywords
Dynamic: license
Dynamic: license-file
Dynamic: requires-dist
Dynamic: summary
